cat_royale/__init__.py
cat_royale/__main__.py
cat_royale/main.py
cat_royale/tasks.txt
cat_royale/__pycache__/__init__.cpython-310.pyc
cat_royale/__pycache__/__main__.cpython-310.pyc
cat_royale/__pycache__/main.cpython-310.pyc
cat_royale/assets/__init__.py
cat_royale/assets/image_locations.json
cat_royale/assets/images/Inventory_Bar.png
cat_royale/assets/images/Inventory_Slot.png
cat_royale/assets/images/Inventory_select.png
cat_royale/assets/images/arrow.png
cat_royale/assets/images/cat.png
cat_royale/assets/images/enemy_cat.png
cat_royale/assets/images/grass.png
cat_royale/assets/images/items.png
cat_royale/assets/images/level00.png
cat_royale/assets/images/loading_screen.png
cat_royale/classes/__init__.py
cat_royale/classes/box.py
cat_royale/classes/character.py
cat_royale/classes/config.py
cat_royale/classes/event_stack.py
cat_royale/classes/functions.py
cat_royale/classes/game_map.py
cat_royale/classes/health_bars.py
cat_royale/classes/inventory.py
cat_royale/classes/item.py
cat_royale/classes/map_reader.py
cat_royale/classes/message_service.py
cat_royale/classes/text_display.py
cat_royale/classes/__pycache__/__init__.cpython-310.pyc
cat_royale/classes/__pycache__/box.cpython-310.pyc
cat_royale/classes/__pycache__/character.cpython-310.pyc
cat_royale/classes/__pycache__/config.cpython-310.pyc
cat_royale/classes/__pycache__/event_stack.cpython-310.pyc
cat_royale/classes/__pycache__/functions.cpython-310.pyc
cat_royale/classes/__pycache__/game_map.cpython-310.pyc
cat_royale/classes/__pycache__/health_bars.cpython-310.pyc
cat_royale/classes/__pycache__/inventory.cpython-310.pyc
cat_royale/classes/__pycache__/item.cpython-310.pyc
cat_royale/classes/__pycache__/item.cpython-311.pyc
cat_royale/classes/__pycache__/map_reader.cpython-310.pyc
cat_royale/classes/__pycache__/map_reader.cpython-311.pyc
cat_royale/classes/__pycache__/message_service.cpython-310.pyc
cat_royale/classes/__pycache__/message_service.cpython-311.pyc
CatRoyale-1.25.dist-info/METADATA
CatRoyale-1.25.dist-info/WHEEL
CatRoyale-1.25.dist-info/entry_points.txt
CatRoyale-1.25.dist-info/top_level.txt
CatRoyale-1.25.dist-info/RECORD
